{
  "unversionedId": "runnable-api/request",
  "id": "runnable-api/request",
  "isDocsHomePage": false,
  "title": "Handling requests",
  "description": "When a Runnable is used to handle an HTTP request, Atmo will bind that request to the Runnable. The req namespace of the Runnable API can then be used to access all of the information about the request. Note if the Runnable is not being used to handle a request, then all methods in the req namespace will return empty or an error.",
  "source": "@site/docs/runnable-api/request.md",
  "sourceDirName": "runnable-api",
  "slug": "/runnable-api/request",
  "permalink": "/docs/runnable-api/request",
  "editUrl": "https://github.com/facebook/docusaurus/edit/main/website/docs/runnable-api/request.md",
  "tags": [],
  "version": "current",
  "frontMatter": {},
  "sidebar": "tutorialSidebar",
  "previous": {
    "title": "Structured logging",
    "permalink": "/docs/runnable-api/logging"
  },
  "next": {
    "title": "Modifying responses",
    "permalink": "/docs/runnable-api/response"
  }
}